README.txt
setup.py
django_rest_guardian/__init__.py
django_rest_guardian/payload_authenticator.py
django_rest_guardian/permission.py
django_rest_guardian/user_authenticator.py
django_rest_guardian.egg-info/PKG-INFO
django_rest_guardian.egg-info/SOURCES.txt
django_rest_guardian.egg-info/dependency_links.txt
django_rest_guardian.egg-info/requires.txt
django_rest_guardian.egg-info/top_level.txt