Metadata-Version: 1.0
Name: django-rest-guardian
Version: 1.1.1
Summary: A django rest middleware which can be used on individual methods of APIViews. The middleware includes user authentication and payload verification
Home-page: https://github.com/droidlife/guardian
Author: Ankur Jain
Author-email: ankurj630@gmail.com
License: LICENSE
Platform: UNKNOWN
